solenoid/__init__.py
solenoid/app.py
solenoid/config.py
solenoid/eureka.py
solenoid/solenoid.py
solenoid/solenoids/__init__.py
solenoid/solenoids/health.py
solenoid/solenoids/info.py
solenoid/solenoids/log.py
solenoid/solenoids/runtime.py
solenoid-0.3.1.dist-info/WHEEL
solenoid-0.3.1.dist-info/METADATA
solenoid-0.3.1.dist-info/RECORD
